unyprot/__init__.py
unyprot/collection.py
unyprot/entry.py
unyprot/miscellaneous.py
unyprot/trash.py
unyprot/uniprot.py
unyprot/utils.py
unyprot-0.1.0.dist-info/LICENSE
unyprot-0.1.0.dist-info/METADATA
unyprot-0.1.0.dist-info/WHEEL
unyprot-0.1.0.dist-info/RECORD
