Metadata-Version: 2.1
Name: unyprot
Version: 0.1.0
Summary: 
Author: glaunay
Author-email: guillaume.launay@ens-lyon.fr
Requires-Python: >=3.9,<4.0
Classifier: Programming Language :: Python :: 3
Classifier: Programming Language :: Python :: 3.9
Classifier: Programming Language :: Python :: 3.10
Classifier: Programming Language :: Python :: 3.11
Classifier: Programming Language :: Python :: 3.12
Requires-Dist: pyproteins (>=2.1.0)
